redis_dumper/__init__.py
redis_dumper/__main__.py
redis_dumper/cli.py
redis_dumper/dumper.py
redis_dumper-0.1.0.dist-info/LICENSE
redis_dumper-0.1.0.dist-info/METADATA
redis_dumper-0.1.0.dist-info/WHEEL
redis_dumper-0.1.0.dist-info/entry_points.txt
redis_dumper-0.1.0.dist-info/top_level.txt
redis_dumper-0.1.0.dist-info/RECORD
