Metadata-Version: 2.1
Name: redis-dumper
Version: 0.1.0
Summary: CLI utility and library for creating encrypted redis dump.
Home-page: https://github.com/DavisDmitry/redis_dumper
Author: Dmitry Davis
Author-email: dmitrydavis@protonmail.com
License: MIT
Platform: UNKNOWN
Classifier: License :: OSI Approved :: MIT License
Classifier: Programming Language :: Python :: 3.7
Classifier: Programming Language :: Python :: 3.8
Classifier: Programming Language :: Python :: 3.9
Classifier: Topic :: Software Development :: Libraries
Classifier: Topic :: Utilities
Requires-Python: >=3.7
Requires-Dist: aioredis (>=1.3.1)
Requires-Dist: click (>=7.1.2)
Requires-Dist: cryptography (>=3.4.7)
